{
  "resourceType": "Parameters",
  "id": "MLParameterResponseExample",
  "meta": {
    "profile": [
      "https://joofio.github.io/obs-cdss-fhir/StructureDefinition/MLParameterResponse"
    ]
  },
  "parameter": [
    {
      "name": "result",
      "valueCoding": {
        "code": "Vaginal"
      }
    },
    {
      "name": "outcome",
      "valueString": "{'Cesariana': '37.23 %', 'Vaginal': '62.77 %'}"
    },
    {
      "name": "decision",
      "valueCoding": {
        "code": "None"
      }
    }
  ]
}